django_password_eye/__init__.py
django_password_eye/apps.py
django_password_eye/fields.py
django_password_eye/widgets.py
django_password_eye/static/django_password_eye/css/django_password_eye.css
django_password_eye/static/django_password_eye/js/django_password_eye.js
django_password_eye/templates/django_password_eye/input.html
django_password_eye/templatetags/__init__.py
django_password_eye/templatetags/password_eye_extras.py
django_password_eye-1.1.4.dist-info/LICENSE
django_password_eye-1.1.4.dist-info/METADATA
django_password_eye-1.1.4.dist-info/WHEEL
django_password_eye-1.1.4.dist-info/top_level.txt
django_password_eye-1.1.4.dist-info/RECORD
