Metadata-Version: 2.1
Name: django-password-eye
Version: 1.1.4
Summary: Password field for Django with the eye icon to show/hide password text
Author-email: Hugo Meza <hugo.meza.macias@gmail.com>
License:                     GNU GENERAL PUBLIC LICENSE
Project-URL: Homepage, https://github.com/hmeza/django_password_eye
Keywords: password,eye,django,field
Classifier: License :: OSI Approved :: MIT License
Classifier: Programming Language :: Python
Classifier: Programming Language :: Python :: 3
License-File: LICENSE
